libravatar.py
pylibravatar-2.0.0.dist-info/METADATA
pylibravatar-2.0.0.dist-info/WHEEL
pylibravatar-2.0.0.dist-info/top_level.txt
pylibravatar-2.0.0.dist-info/RECORD
