Metadata-Version: 2.4
Name: pyLibravatar
Version: 2.0.0
Summary: Python module for Libravatar
Author-email: Francois Marier <francois@libravatar.org>, Oliver Falk <oliver@linux-kernel.at>
Maintainer-email: Oliver Falk <oliver@linux-kernel.at>
License-Expression: MIT
Project-URL: Homepage, https://github.com/libravatar/pylibravatar
Project-URL: Repository, https://github.com/libravatar/pylibravatar
Keywords: libravatar,avatars,autonomous,social,federated
Classifier: Development Status :: 5 - Production/Stable
Classifier: Intended Audience :: Developers
Classifier: Operating System :: OS Independent
Classifier: Programming Language :: Python :: 3
Classifier: Programming Language :: Python :: 3.10
Classifier: Programming Language :: Python :: 3.11
Classifier: Programming Language :: Python :: 3.12
Classifier: Programming Language :: Python :: 3.13
Classifier: Programming Language :: Python :: 3.14
Classifier: Topic :: Software Development :: Libraries :: Python Modules
Requires-Python: >=3.8
Requires-Dist: dnspython>=2.0.0
Provides-Extra: dev
Requires-Dist: pytest; extra == "dev"
Requires-Dist: mypy; extra == "dev"
Requires-Dist: build; extra == "dev"
Requires-Dist: twine; extra == "dev"
